LICENSE
MANIFEST.in
README.md
setup.py
burp_server/__init__.py
burp_server.egg-info/PKG-INFO
burp_server.egg-info/SOURCES.txt
burp_server.egg-info/dependency_links.txt
burp_server.egg-info/requires.txt
burp_server.egg-info/top_level.txt
mitmproxy/__init__.py
mitmproxy/addonmanager.py
mitmproxy/certs.py
mitmproxy/command.py
mitmproxy/command_lexer.py
mitmproxy/connections.py
mitmproxy/controller.py
mitmproxy/ctx.py
mitmproxy/eventsequence.py
mitmproxy/exceptions.py
mitmproxy/flow.py
mitmproxy/flowfilter.py
mitmproxy/http.py
mitmproxy/log.py
mitmproxy/master.py
mitmproxy/options.py
mitmproxy/optmanager.py
mitmproxy/py.typed
mitmproxy/stateobject.py
mitmproxy/tcp.py
mitmproxy/types.py
mitmproxy/version.py
mitmproxy/websocket.py
mitmproxy/addons/__init__.py
mitmproxy/addons/anticache.py
mitmproxy/addons/anticomp.py
mitmproxy/addons/asgiapp.py
mitmproxy/addons/block.py
mitmproxy/addons/browser.py
mitmproxy/addons/check_ca.py
mitmproxy/addons/clientplayback.py
mitmproxy/addons/command_history.py
mitmproxy/addons/core.py
mitmproxy/addons/cut.py
mitmproxy/addons/disable_h2c.py
mitmproxy/addons/dumper.py
mitmproxy/addons/eventstore.py
mitmproxy/addons/export.py
mitmproxy/addons/intercept.py
mitmproxy/addons/keepserving.py
mitmproxy/addons/maplocal.py
mitmproxy/addons/mapremote.py
mitmproxy/addons/modifybody.py
mitmproxy/addons/modifyheaders.py
mitmproxy/addons/onboarding.py
mitmproxy/addons/proxyauth.py
mitmproxy/addons/readfile.py
mitmproxy/addons/save.py
mitmproxy/addons/script.py
mitmproxy/addons/serverplayback.py
mitmproxy/addons/session.py
mitmproxy/addons/stickyauth.py
mitmproxy/addons/stickycookie.py
mitmproxy/addons/streambodies.py
mitmproxy/addons/termlog.py
mitmproxy/addons/termstatus.py
mitmproxy/addons/upstream_auth.py
mitmproxy/addons/view.py
mitmproxy/addons/onboardingapp/__init__.py
mitmproxy/contentviews/__init__.py
mitmproxy/contentviews/auto.py
mitmproxy/contentviews/base.py
mitmproxy/contentviews/css.py
mitmproxy/contentviews/hex.py
mitmproxy/contentviews/javascript.py
mitmproxy/contentviews/json.py
mitmproxy/contentviews/msgpack.py
mitmproxy/contentviews/multipart.py
mitmproxy/contentviews/protobuf.py
