Metadata-Version: 2.1
Name: burp_server
Version: 0.1.2
Summary: Annotated burp interfaces for python/jython
Home-page: https://github.com/
Author: yan wang
Author-email: 1449349985@qq.com
License: MIT
Classifier: License :: OSI Approved :: MIT License
Classifier: Programming Language :: Python
Classifier: Programming Language :: Python :: 3
Classifier: Programming Language :: Python :: 3.6
Classifier: Programming Language :: Python :: Implementation :: CPython
Classifier: Programming Language :: Python :: Implementation :: PyPy
Requires-Python: >=3.6.0
License-File: LICENSE
Requires-Dist: pyasn1==0.4.8
Requires-Dist: pyOpenSSL
Requires-Dist: certifi
Requires-Dist: kaitaistruct
Requires-Dist: blinker==1.4
